dnschecker/__init__.py
dnschecker/core.py
dnschecker-0.1.2.dist-info/licenses/LICENSE
dnschecker-0.1.2.dist-info/METADATA
dnschecker-0.1.2.dist-info/WHEEL
dnschecker-0.1.2.dist-info/entry_points.txt
dnschecker-0.1.2.dist-info/top_level.txt
dnschecker-0.1.2.dist-info/RECORD
