Metadata-Version: 2.4
Name: dnschecker
Version: 0.1.2
Summary: A powerful Python CLI tool for querying and analyzing DNS records across multiple domains with advanced search, custom DNS servers, and color-coded output for network troubleshooting and auditing.
Author-email: Daniel Fuhrer <daniel@danielf.ch>
Maintainer-email: Daniel Fuhrer <daniel@danielf.ch>
License: MIT
Project-URL: Homepage, https://github.com/fuhdan/dns-checker
Project-URL: Bug Reports, https://github.com/fuhdan/dns-checker/issues
Project-URL: Source, https://github.com/fuhdan/dns-checker
Keywords: dns,cli,network,troubleshooting,devops,sysadmin,records
Classifier: Development Status :: 4 - Beta
Classifier: Intended Audience :: System Administrators
Classifier: Intended Audience :: Developers
Classifier: Topic :: Internet :: Name Service (DNS)
Classifier: Topic :: System :: Networking
Classifier: Topic :: System :: Systems Administration
Classifier: License :: OSI Approved :: MIT License
Classifier: Programming Language :: Python :: 3
Classifier: Programming Language :: Python :: 3.7
Classifier: Programming Language :: Python :: 3.8
Classifier: Programming Language :: Python :: 3.9
Classifier: Programming Language :: Python :: 3.10
Classifier: Programming Language :: Python :: 3.11
Classifier: Programming Language :: Python :: 3.12
Classifier: Operating System :: OS Independent
Classifier: Environment :: Console
Requires-Python: >=3.7
License-File: LICENSE
Requires-Dist: dnspython>=2.4.2
Dynamic: license-file
